<?xml version="1.0"?>
<opencv_storage>
<cascade>
  <stageType>BOOST</stageType>
  <featureType>LBP</featureType>
  <height>48</height>
  <width>48</width>
  <stageParams>
    <boostType>GAB</boostType>
    <minHitRate>9.9500000476837158e-01</minHitRate>
    <maxFalseAlarm>5.0000000000000000e-01</maxFalseAlarm>
    <weightTrimRate>9.4999999999999996e-01</weightTrimRate>
    <maxDepth>1</maxDepth>
    <maxWeakCount>100</maxWeakCount></stageParams>
  <featureParams>
    <maxCatCount>256</maxCatCount>
    <featSize>1</featSize></featureParams>
  <stageNum>14</stageNum>
  <stages>
    <!-- stage 0 -->
    <_>
      <maxWeakCount>2</maxWeakCount>
      <stageThreshold>-3.8698452711105347e-01</stageThreshold>
      <weakClassifiers>
        <_>
          <internalNodes>
            0 -1 24 -174531336 -180016 -620243489 -2404131 -131926786
            -6574389 -1952776193 -270849</internalNodes>
          <leafValues>
            -9.4316160678863525e-01 6.4302057027816772e-01</leafValues></_>
        <_>
          <internalNodes>
            0 -1 42 -182724097 -147195399 1564605951 2144468471
            -108344833 -70546759 978444287 536828735</internalNodes>
          <leafValues>
            -8.3751136064529419e-01 5.5617713928222656e-01</leafValues></_></weakClassifiers></_>
    <!-- stage 1 -->
    <_>
      <maxWeakCount>4</maxWeakCount>
      <stageThreshold>-5.5284047126770020e-01</stageThreshold>
      <weakClassifiers>
        <_>
          <internalNodes>
            0 -1 56 -1 -1569 -686292993 1610611967 -135009285 -72407329
            -6554657 2147482619</internalNodes>
          <leafValues>
            -8.4712797403335571e-01 4.8798212409019470e-01</leafValues></_>
        <_>
          <internalNodes>
            0 -1 14 -243219201 -6172272 2096222975 -2784267 421548279
            -15006576 1883299839 -8913413</internalNodes>
          <leafValues>
            -8.0365115404129028e-01 5.9889775514602661e-01</leafValues></_>
        <_>
          <internalNodes>
            0 -1 11 -1837318 -278674937 1120092859 -620539405 1191385410
            -110890161 1124548915 -11010481</internalNodes>
          <leafValues>
            -7.2779238224029541e-01 5.8921074867248535e-01</leafValues></_>
        <_>
          <internalNodes>
            0 -1 43 -2106369 -539127088 -715524619 2002745337 -2425121
            -1080307489 999865343 2136943581</internalNodes>
          <leafValues>
            -8.2638216018676758e-01 5.6786513328552246e-01</leafValues></_></weakClassifiers></_>
    <!-- stage 2 -->
    <_>
      <maxWeakCount>4</maxWeakCount>
      <stageThreshold>-5.2682775259017944e-01</stageThreshold>
      <weakClassifiers>
        <_>
          <internalNodes>
            0 -1 25 -67578372 -107359975 -216317603 -8564301 -837252609
            -1446443973 -1431598705 -1146365521</internalNodes>
          <leafValues>
            -9.1566264629364014e-01 4.1035857796669006e-01</leafValues></_>
        <_>
          <internalNodes>
            0 -1 60 -8389382 291604488 285335569 421380239 -1685354582
            -1349838837 -1727411253 -1999902241</internalNodes>
          <leafValues>
            -7.4382561445236206e-01 5.3297454118728638e-01</leafValues></_>
        <_>
          <internalNodes>
            0 -1 29 -673974819 -649866276 -1793781477 1599549689
            -893670694 -1445289842 362334959 459240415</internalNodes>
          <leafValues>
            -7.7358597517013550e-01 5.5585706233978271e-01</leafValues></_>
        <_>
          <internalNodes>
            0 -1 20 -1180609285 2009403728 1446695153 2075514129
            -1735606113 -1416936545 -88426497 -21302807</internalNodes>
          <leafValues>
            -6.7959684133529663e-01 6.2944632768630981e-01</leafValues></_></weakClassifiers></_>
    <!-- stage 3 -->
    <_>
      <maxWeakCount>5</maxWeakCount>
      <stageThreshold>-1.4026234149932861e+00</stageThreshold>
      <weakClassifiers>
        <_>
          <internalNodes>
            0 -1 54 -235015426 -2256678 -1048559229 -247336310
            -265559921 -494297080 -343676273 -68177153</internalNodes>
          <leafValues>
            -7.1856784820556641e-01 4.5431789755821228e-01</leafValues></_>
        <_>
          <internalNodes>
            0 -1 62 -35652150 -773863228 1090766848 515602 -86776630
            -65036126 -855385906 -842011953</internalNodes>
          <leafValues>
            -7.0489668846130371e-01 4.4886392354965210e-01</leafValues></_>
        <_>
          <internalNodes>
            0 -1 52 -1076734725 -43584278 1460853207 2145181430
            -104147201 2074876042 441182971 524236287</internalNodes>
          <leafValues>
            -8.6538225412368774e-01 3.7828528881072998e-01</leafValues></_>
        <_>
          <internalNodes>
            0 -1 18 -1181101896 -72494600 -55271043 -36056883 740864251
            -43300822 -1160203621 -78591249</internalNodes>
          <leafValues>
            -7.5273871421813965e-01 4.3823951482772827e-01</leafValues></_>
        <_>
          <internalNodes>
            0 -1 6 -674300678 -578048246 1074323835 -615545848
            1124356130 -91946672 1224829819 -11575485</internalNodes>
          <leafValues>
            -7.2682398557662964e-01 4.4798386096954346e-01</leafValues></_></weakClassifiers></_>
    <!-- stage 4 -->
    <_>
      <maxWeakCount>4</maxWeakCount>
      <stageThreshold>-7.6540410518646240e-01</stageThreshold>
      <weakClassifiers>
        <_>
          <internalNodes>
            0 -1 48 -2099201 -37227877 294376723 2145105499 -89142821
            2066125451 2146956207 2013265919</internalNodes>
          <leafValues>
            -8.3084112405776978e-01 4.1827955842018127e-01</leafValues></_>
        <_>
          <internalNodes>
            0 -1 32 -2098946 -589977540 1763807733 1575992383 -154681349
            -1679868358 -604788241 469743275</internalNodes>
          <leafValues>
            -7.1466743946075439e-01 4.3000280857086182e-01</leafValues></_>
        <_>
          <internalNodes>
            0 -1 44 -84942341 -2124929 -1690183009 1461152735 -9445377
            -343848262 1396701951 1998584731</internalNodes>
          <leafValues>
            -8.1010967493057251e-01 4.3746840953826904e-01</leafValues></_>
        <_>
          <internalNodes>
            0 -1 2 -10501106 -34618354 -494892512 -498416498 -45194472
            -364769790 -1295605121 -79213497</internalNodes>
          <leafValues>
            -7.3286777734756470e-01 4.4554385542869568e-01</leafValues></_></weakClassifiers></_>
    <!-- stage 5 -->
    <_>
      <maxWeakCount>5</maxWeakCount>
      <stageThreshold>-1.1978405714035034e+00</stageThreshold>
      <weakClassifiers>
        <_>
          <internalNodes>
            0 -1 45 -242589986 -69254676 -1182731267 -7373860 -105988418
            -73139653 -302072069 -271908</internalNodes>
          <leafValues>
            -8.5884797573089600e-01 3.1596720218658447e-01</leafValues></_>
        <_>
          <internalNodes>
            0 -1 53 -8650838 -1415386496 -747121903 -170528343
            -622075170 -5527333 -68422223 -3073</internalNodes>
          <leafValues>
            -6.1208075284957886e-01 5.3456258773803711e-01</leafValues></_>
        <_>
          <internalNodes>
            0 -1 1 -280829190 -9500456 134355 -11588977 -822021136
            -88160005 1531249911 -10529561</internalNodes>
          <leafValues>
            -7.0945650339126587e-01 4.3187522888183594e-01</leafValues></_>
        <_>
          <internalNodes>
            0 -1 39 -1041002238 -212664085 -1021265220 -779721920
            -796397125 -928496508 -527979855 -3149912</internalNodes>
          <leafValues>
            -5.4295128583908081e-01 5.8814603090286255e-01</leafValues></_>
        <_>
          <internalNodes>
            0 -1 28 -70167173 -918256226 959730421 1414877649 -434586800
            -1165260726 344772343 455017147</internalNodes>
          <leafValues>
            -7.9065102338790894e-01 4.1646093130111694e-01</leafValues></_></weakClassifiers></_>
    <!-- stage 6 -->
    <_>
      <maxWeakCount>4</maxWeakCount>
      <stageThreshold>-8.3412283658981323e-01</stageThreshold>
      <weakClassifiers>
        <_>
          <internalNodes>
            0 -1 66 -301994038 -775568999 17482752 1146014210 -874517950
            -708623469 -871372341 -840963105</internalNodes>
          <leafValues>
            -7.3204421997070312e-01 3.2275712490081787e-01</leafValues></_>
        <_>
          <internalNodes>
            0 -1 49 -562143650 -23215265 -124584198 -21318773 -663925234
            -19237890 -118829362 -17069233</internalNodes>
          <leafValues>
            -6.1307424306869507e-01 4.6713006496429443e-01</leafValues></_>
        <_>
          <internalNodes>
            0 -1 22 -1145514760 -134394432 -1749093739 -918139
            -1095042305 -4481 -1432569205 -6230787</internalNodes>
          <leafValues>
            -8.6245805025100708e-01 3.2237070798873901e-01</leafValues></_>
        <_>
          <internalNodes>
            0 -1 37 -81799429 -1030569525 -1068318318 425652547
            -77866416 74017 1242729160 2013260415</internalNodes>
          <leafValues>
            -7.6155197620391846e-01 3.8954168558120728e-01</leafValues></_></weakClassifiers></_>
    <!-- stage 7 -->
    <_>
      <maxWeakCount>5</maxWeakCount>
      <stageThreshold>-1.1908893585205078e+00</stageThreshold>
      <weakClassifiers>
        <_>
          <internalNodes>
            0 -1 12 -1953775472 -1685892880 -802429071 -498084496
            -1105475111 -1207582560 -1681155079 -7355936</internalNodes>
          <leafValues>
            -7.4113136529922485e-01 2.8526645898818970e-01</leafValues></_>
        <_>
          <internalNodes>
            0 -1 46 -576718628 -795566884 1938499677 1565914909
            -698616114 -1431640662 -1659897848 -1945110321</internalNodes>
          <leafValues>
            -7.7517557144165039e-01 3.2705509662628174e-01</leafValues></_>
        <_>
          <internalNodes>
            0 -1 65 -303113750 -355827480 456781744 -705189920
            -1353389137 -285505126 -84028446 -134218753</internalNodes>
          <leafValues>
            -5.5689734220504761e-01 5.1148825883865356e-01</leafValues></_>
        <_>
          <internalNodes>
            0 -1 31 -178266381 -10511113 1900351963 1472053527
            -1559842114 -102825834 453741497 461343483</internalNodes>
          <leafValues>
            -7.2597515583038330e-01 4.4680181145668030e-01</leafValues></_>
        <_>
          <internalNodes>
            0 -1 38 -1052524286 -481959798 -1073020924 -75385438
            -1308784123 -1467479550 -1215987583 -69229693</internalNodes>
          <leafValues>
            -5.6232613325119019e-01 5.4716545343399048e-01</leafValues></_></weakClassifiers></_>
    <!-- stage 8 -->
    <_>
      <maxWeakCount>5</maxWeakCount>
      <stageThreshold>-1.3186672925949097e+00</stageThreshold>
      <weakClassifiers>
        <_>
          <internalNodes>
            0 -1 4 -265558 -297038642 1107738638 -720649333 1951596271
            -163073943 1196908362 -11010373</internalNodes>
          <leafValues>
            -6.9204151630401611e-01 3.5545024275779724e-01</leafValues></_>
        <_>
          <internalNodes>
            0 -1 26 -1111991048 -1107470337 -671623201 -527369
            -1298743618 -1111526979 -80742173 2143253471</internalNodes>
          <leafValues>
            -8.0466634035110474e-01 3.4251034259796143e-01</leafValues></_>
        <_>
          <internalNodes>
            0 -1 3 -588341050 -21106661 -2008250162 -1140407653
            -1078460408 -1161417339 -460532225 -33620241</internalNodes>
          <leafValues>
            -6.2724846601486206e-01 4.3770730495452881e-01</leafValues></_>
        <_>
          <internalNodes>
            0 -1 47 -764968446 1112148574 -1806041022 -716029601
            -1060127834 -1603501152 21179291 903867311</internalNodes>
          <leafValues>
            -6.7522436380386353e-01 4.3559530377388000e-01</leafValues></_>
        <_>
          <internalNodes>
            0 -1 27 -1196403207 -201492516 1930762779 -153788219
            -1095175745 -1091632479 -1433374501 -361297</internalNodes>
          <leafValues>
            -7.1770811080932617e-01 4.3302160501480103e-01</leafValues></_></weakClassifiers></_>
    <!-- stage 9 -->
    <_>
      <maxWeakCount>6</maxWeakCount>
      <stageThreshold>-1.4796240329742432e+00</stageThreshold>
      <weakClassifiers>
        <_>
          <internalNodes>
            0 -1 8 -84938022 -236228594 72557747 -553389301 1079174050
            -1554783473 1240678639 -11010465</internalNodes>
          <leafValues>
            -7.3767256736755371e-01 2.5152128934860229e-01</leafValues></_>
        <_>
          <internalNodes>
            0 -1 10 -1349779982 -1347950400 -521963054 -303058224
            -476331605 -1448885565 -270810127 -268440848</internalNodes>
          <leafValues>
            -5.9165805578231812e-01 4.2970246076583862e-01</leafValues></_>
        <_>
          <internalNodes>
            0 -1 51 -304360193 -1157926195 372309981 1606375391
            -741959174 782898827 319667195 389960153</internalNodes>
          <leafValues>
            -8.1834203004837036e-01 3.1660133600234985e-01</leafValues></_>
        <_>
          <internalNodes>
            0 -1 17 -67156738 -604103332 -386491171 -116781637 -637944
            -682274994 -4274721 -270657</internalNodes>
          <leafValues>
            -4.2840817570686340e-01 6.5023356676101685e-01</leafValues></_>
        <_>
          <internalNodes>
            0 -1 63 -35652118 -707419916 537191698 2089014 -1582096253
            -664800750 1091011531 -1057237265</internalNodes>
          <leafValues>
            -5.8558076620101929e-01 4.5234456658363342e-01</leafValues></_>
        <_>
          <internalNodes>
            0 -1 16 -201648933 -1281240744 -56143271 -682518027
            1073737869 1058777803 -255729521 -169740037</internalNodes>
          <leafValues>
            -5.3154742717742920e-01 5.4919713735580444e-01</leafValues></_></weakClassifiers></_>
    <!-- stage 10 -->
    <_>
      <maxWeakCount>6</maxWeakCount>
      <stageThreshold>-8.4398096799850464e-01</stageThreshold>
      <weakClassifiers>
        <_>
          <internalNodes>
            0 -1 21 -1164190477 -3960621 -37426401 -143887 -1466965249
            -873524545 -287462929 -459779</internalNodes>
          <leafValues>
            -6.3456791639328003e-01 3.4522292017936707e-01</leafValues></_>
        <_>
          <internalNodes>
            0 -1 36 -790129274 -228605766 -548517838 2012194894
            -1060654946 -1804820304 -742132908 1400366071</internalNodes>
          <leafValues>
            -6.8490874767303467e-01 3.5796377062797546e-01</leafValues></_>
        <_>
          <internalNodes>
            0 -1 19 832721151 -9995272 -84282399 -8396299 -1091643173
            -341084081 -89457749 -67109385</internalNodes>
          <leafValues>
            -5.4994881153106689e-01 4.5217502117156982e-01</leafValues></_>
        <_>
          <internalNodes>
            0 -1 58 -636251143 -270846895 362203544 -547532472
            1929558522 -1618865734 1526839802 521998812</internalNodes>
          <leafValues>
            -7.6789873838424683e-01 3.7535223364830017e-01</leafValues></_>
        <_>
          <internalNodes>
            0 -1 67 -1146423110 -1147395456 -2011664144 -1280461792
            -1725906808 -1700166596 -1431777056 -5251588</internalNodes>
          <leafValues>
            -6.0483163595199585e-01 4.4640994071960449e-01</leafValues></_>
        <_>
          <internalNodes>
            0 -1 9 -112064012 -208209841 -1538125602 -85325158
            -675544932 -359590472 -657499185 -68281377</internalNodes>
          <leafValues>
            -6.1947143077850342e-01 4.1626021265983582e-01</leafValues></_></weakClassifiers></_>
    <!-- stage 11 -->
    <_>
      <maxWeakCount>6</maxWeakCount>
      <stageThreshold>-1.1485683917999268e+00</stageThreshold>
      <weakClassifiers>
        <_>
          <internalNodes>
            0 -1 64 -83889470 836752627 -1878929392 539682026
            -1848129534 -499675947 -1275351157 -1157628961</internalNodes>
          <leafValues>
            -7.3326468467712402e-01 2.0602527260780334e-01</leafValues></_>
        <_>
          <internalNodes>
            0 -1 34 -40632833 -6425188 2110102783 1427621053 -55383361
            -561319245 2067332863 439315391</internalNodes>
          <leafValues>
            -7.8315335512161255e-01 2.6352980732917786e-01</leafValues></_>
        <_>
          <internalNodes>
            0 -1 30 -467718 -2304728 -609268803 -3413547 -1078266117
            -1141997409 -328225 -1146430212</internalNodes>
          <leafValues>
            -7.2230041027069092e-01 3.2022663950920105e-01</leafValues></_>
        <_>
          <internalNodes>
            0 -1 15 -621297734 -375659122 1090695194 -619495157
            1344439467 -1459486195 1087021483 -546079973</internalNodes>
          <leafValues>
            -5.8626306056976318e-01 4.4801759719848633e-01</leafValues></_>
        <_>
          <internalNodes>
            0 -1 55 -745573810 -693641076 1530844664 1444446360
            -756497126 -728742708 463835837 1602745342</internalNodes>
          <leafValues>
            -6.9994187355041504e-01 3.5311242938041687e-01</leafValues></_>
        <_>
          <internalNodes>
            0 -1 13 -147377940 -190166620 688158 379752563 1653348488
            2018384008 -1476218708 -31000129</internalNodes>
          <leafValues>
            -6.0136795043945312e-01 3.9453810453414917e-01</leafValues></_></weakClassifiers></_>
    <!-- stage 12 -->
    <_>
      <maxWeakCount>6</maxWeakCount>
      <stageThreshold>-8.2293713092803955e-01</stageThreshold>
      <weakClassifiers>
        <_>
          <internalNodes>
            0 -1 0 -273685769 -308346254 -271005185 -72154973 -204734469
            -104206671 -83886337 -1084463</internalNodes>
          <leafValues>
            -5.9052056074142456e-01 3.6465638875961304e-01</leafValues></_>
        <_>
          <internalNodes>
            0 -1 50 -2776338 -205920266 -802586234 -214720114
            -2105228545 -1567965054 -358489457 -284022</internalNodes>
          <leafValues>
            -5.7664054632186890e-01 4.1432788968086243e-01</leafValues></_>
        <_>
          <internalNodes>
            0 -1 35 -546153255 -8030184 1496940023 1507802589 -75309382
            -84005729 1498005503 521891579</internalNodes>
          <leafValues>
            -7.8687208890914917e-01 3.1320288777351379e-01</leafValues></_>
        <_>
          <internalNodes>
            0 -1 40 285682346 -349865830 -1215659962 -91483392
            -1447319158 -1558134654 -1314815765 -1141535862</internalNodes>
          <leafValues>
            -6.0486650466918945e-01 4.2185285687446594e-01</leafValues></_>
        <_>
          <internalNodes>
            0 -1 59 -1348017494 -1928928350 1360203744 -12224175
            -1454799958 -352012134 -241668432 -1048843</internalNodes>
          <leafValues>
            -5.7120424509048462e-01 4.6980661153793335e-01</leafValues></_>
        <_>
          <internalNodes>
            0 -1 41 -729296734 -143996164 1347475618 -208481332
            -1050414354 -800448272 -230317276 1373064068</internalNodes>
          <leafValues>
            -7.3905360698699951e-01 3.4374567866325378e-01</leafValues></_></weakClassifiers></_>
    <!-- stage 13 -->
    <_>
      <maxWeakCount>6</maxWeakCount>
      <stageThreshold>-8.4895902872085571e-01</stageThreshold>
      <weakClassifiers>
        <_>
          <internalNodes>
            0 -1 33 -1815121202 -145364721 -601699898 -136846965
            -705309761 -57622230 -101077329 -34289722</internalNodes>
          <leafValues>
            -7.0032274723052979e-01 2.8345167636871338e-01</leafValues></_>
        <_>
          <internalNodes>
            0 -1 57 -721683336 1078827092 922990641 286093853 -385899026
            -924276054 -658274099 -842008069</internalNodes>
          <leafValues>
            -7.4240881204605103e-01 2.8520575165748596e-01</leafValues></_>
        <_>
          <internalNodes>
            0 -1 23 -1145417217 -5017249 -68642901 1962275037
            -1080970113 -206147215 -118244161 2147219705</internalNodes>
          <leafValues>
            -6.2133210897445679e-01 3.6012434959411621e-01</leafValues></_>
        <_>
          <internalNodes>
            0 -1 5 -169879862 -290987514 -2143039478 -616050197
            -166529403 50512191 89516552 -179837953</internalNodes>
          <leafValues>
            -5.2975112199783325e-01 4.7268939018249512e-01</leafValues></_>
        <_>
          <internalNodes>
            0 -1 61 -273707038 1981233075 -194577712 -218378001
            -82063257 -1281797944 1637769959 2012731611</internalNodes>
          <leafValues>
            -6.4985603094100952e-01 3.7151145935058594e-01</leafValues></_>
        <_>
          <internalNodes>
            0 -1 7 -988817430 -1591581246 -1582700560 2139478240
            1510209996 -1110867129 -846333023 -292562042</internalNodes>
          <leafValues>
            -5.7295960187911987e-01 4.2328190803527832e-01</leafValues></_></weakClassifiers></_></stages>
  <features>
    <_>
      <rect>
        0 3 7 8</rect></_>
    <_>
      <rect>
        0 12 8 6</rect></_>
    <_>
      <rect>
        0 22 5 5</rect></_>
    <_>
      <rect>
        0 30 6 4</rect></_>
    <_>
      <rect>
        1 16 4 5</rect></_>
    <_>
      <rect>
        1 17 4 5</rect></_>
    <_>
      <rect>
        1 17 7 7</rect></_>
    <_>
      <rect>
        2 7 6 3</rect></_>
    <_>
      <rect>
        2 17 5 5</rect></_>
    <_>
      <rect>
        2 26 7 7</rect></_>
    <_>
      <rect>
        3 3 6 5</rect></_>
    <_>
      <rect>
        3 14 5 6</rect></_>
    <_>
      <rect>
        4 0 3 9</rect></_>
    <_>
      <rect>
        4 20 2 8</rect></_>
    <_>
      <rect>
        5 16 10 5</rect></_>
    <_>
      <rect>
        5 17 4 6</rect></_>
    <_>
      <rect>
        6 19 10 3</rect></_>
    <_>
      <rect>
        6 25 2 4</rect></_>
    <_>
      <rect>
        9 16 7 5</rect></_>
    <_>
      <rect>
        11 17 9 4</rect></_>
    <_>
      <rect>
        11 18 9 4</rect></_>
    <_>
      <rect>
        11 19 6 4</rect></_>
    <_>
      <rect>
        12 17 7 5</rect></_>
    <_>
      <rect>
        13 13 7 4</rect></_>
    <_>
      <rect>
        13 15 8 6</rect></_>
    <_>
      <rect>
        14 11 6 8</rect></_>
    <_>
      <rect>
        14 13 7 5</rect></_>
    <_>
      <rect>
        14 15 6 5</rect></_>
    <_>
      <rect>
        14 16 6 1</rect></_>
    <_>
      <rect>
        15 13 5 1</rect></_>
    <_>
      <rect>
        15 18 7 5</rect></_>
    <_>
      <rect>
        15 31 3 1</rect></_>
    <_>
      <rect>
        16 11 9 9</rect></_>
    <_>
      <rect>
        16 17 3 4</rect></_>
    <_>
      <rect>
        18 14 3 1</rect></_>
    <_>
      <rect>
        18 31 4 1</rect></_>
    <_>
      <rect>
        19 20 2 3</rect></_>
    <_>
      <rect>
        19 26 1 2</rect></_>
    <_>
      <rect>
        20 14 2 6</rect></_>
    <_>
      <rect>
        20 16 2 5</rect></_>
    <_>
      <rect>
        20 16 3 5</rect></_>
    <_>
      <rect>
        20 18 2 3</rect></_>
    <_>
      <rect>
        20 32 3 1</rect></_>
    <_>
      <rect>
        21 14 3 1</rect></_>
    <_>
      <rect>
        21 15 1 1</rect></_>
    <_>
      <rect>
        21 17 5 5</rect></_>
    <_>
      <rect>
        21 18 9 6</rect></_>
    <_>
      <rect>
        21 21 2 3</rect></_>
    <_>
      <rect>
        21 29 1 2</rect></_>
    <_>
      <rect>
        24 5 8 4</rect></_>
    <_>
      <rect>
        24 11 2 9</rect></_>
    <_>
      <rect>
        24 15 3 1</rect></_>
    <_>
      <rect>
        24 31 3 1</rect></_>
    <_>
      <rect>
        24 31 8 4</rect></_>
    <_>
      <rect>
        25 11 2 9</rect></_>
    <_>
      <rect>
        25 20 2 3</rect></_>
    <_>
      <rect>
        25 30 1 1</rect></_>
    <_>
      <rect>
        27 18 7 5</rect></_>
    <_>
      <rect>
        27 30 3 1</rect></_>
    <_>
      <rect>
        29 31 6 2</rect></_>
    <_>
      <rect>
        30 15 5 6</rect></_>
    <_>
      <rect>
        31 17 4 2</rect></_>
    <_>
      <rect>
        32 14 5 6</rect></_>
    <_>
      <rect>
        33 12 4 7</rect></_>
    <_>
      <rect>
        33 12 5 5</rect></_>
    <_>
      <rect>
        33 29 5 2</rect></_>
    <_>
      <rect>
        36 16 4 5</rect></_>
    <_>
      <rect>
        36 20 2 9</rect></_></features></cascade>
</opencv_storage>
